{"data_mtime": 1677478520, "dep_lines": [21, 32, 33, 34, 35, 37, 42, 1, 2, 3, 4, 19, 40, 1, 1, 1, 1, 1, 1, 1, 1, 1, 1, 1, 1, 1, 1, 1, 1, 1, 1, 1, 1, 1, 1, 1, 1, 1, 1, 1, 1, 1, 1, 1, 1, 1, 1, 1, 1, 1], "dep_prios": [5, 5, 5, 5, 5, 5, 25, 10, 5, 5, 5, 10, 25, 5, 20, 20, 20, 20, 20, 20, 20, 20, 20, 20, 30, 30, 30, 30, 30, 30, 30, 30, 30, 30, 20, 20, 20, 20, 20, 20, 20, 20, 20, 20, 20, 20, 20, 20, 20, 20], "dependencies": ["_pytest._code.code", "_pytest._io", "_pytest.compat", "_pytest.config", "_pytest.nodes", "_pytest.outcomes", "_pytest.runner", "os", "io", "pprint", "typing", "attr", "typing_extensions", "builtins", "html", "sys", "copy", "types", "traceback", "collections", "warnings", "string", "itertools", "re", "_collections_abc", "_pytest._code", "_pytest._io.terminalwriter", "_pytest.config.compat", "_typeshed", "abc", "array", "attr._typing_compat", "ctypes", "mmap", "torch.ao.nn.quantized.dynamic", "torch.nn", "numpy", "torch.nn.intrinsic.quantized", "torch.ao.nn.quantized", "torch.distributed", "torch.ao.nn", "torch.nn.intrinsic", "torch.nn.intrinsic.qat", "multiprocessing.reduction", "torch.ao.nn.quantized.reference", "torch.nn.intrinsic.quantized.dynamic", "torch.ao.nn.qat.dynamic", "torch", "torch.ao.nn.qat", "torch.nn.functional"], "hash": "46ab220f182f5fc9f0290a7f29f7d6a823289854b750debcbe8e0aa2d8b23844", "id": "_pytest.reports", "ignore_all": true, "interface_hash": "9702e02d7485de0368fdb9413c68feb49e75c62c11b32d42739a3047557efece", "mtime": 1677478400, "options": {"allow_redefinition": false, "allow_untyped_globals": false, "always_false": [], "always_true": [], "bazel": false, "check_untyped_defs": false, "disable_bytearray_promotion": false, "disable_error_code": [], "disable_memoryview_promotion": false, "disabled_error_codes": [], "disallow_any_decorated": false, "disallow_any_explicit": false, "disallow_any_expr": false, "disallow_any_generics": false, "disallow_any_unimported": false, "disallow_incomplete_defs": false, "disallow_subclassing_any": false, "disallow_untyped_calls": false, "disallow_untyped_decorators": false, "disallow_untyped_defs": false, "enable_error_code": [], "enabled_error_codes": [], "follow_imports": "normal", "follow_imports_for_stubs": false, "ignore_errors": false, "ignore_missing_imports": false, "implicit_optional": false, "implicit_reexport": true, "local_partial_types": false, "mypyc": false, "platform": "linux", "plugins": [], "strict_concatenate": false, "strict_equality": false, "strict_optional": true, "warn_no_return": true, "warn_return_any": false, "warn_unreachable": false, "warn_unused_ignores": false}, "path": "/home/adi/.pyenv/versions/3.7.16/lib/python3.7/site-packages/_pytest/reports.py", "plugin_data": null, "size": 20041, "suppressed": [], "version_id": "1.0.1"}