{"data_mtime": 1677478520, "dep_lines": [24, 28, 19, 23, 27, 29, 30, 33, 41, 42, 2, 3, 4, 5, 17, 23, 39, 1, 1, 1, 1, 1, 1, 1, 1, 1, 1, 1, 1, 1, 1, 1, 1, 1, 1, 1, 1, 1, 1, 1, 1, 1, 1, 1, 1, 1, 1, 1, 1, 1, 1, 1, 1, 1, 1, 1, 1, 1, 1], "dep_prios": [5, 5, 5, 10, 5, 5, 5, 5, 25, 25, 10, 10, 10, 5, 10, 20, 25, 5, 20, 20, 20, 20, 20, 20, 20, 20, 20, 20, 30, 30, 30, 30, 30, 30, 30, 30, 30, 30, 30, 30, 30, 30, 30, 20, 20, 20, 20, 20, 20, 20, 20, 20, 20, 20, 20, 20, 20, 20, 20], "dependencies": ["_pytest._code.code", "_pytest.config.argparsing", "_pytest.reports", "_pytest.timing", "_pytest.compat", "_pytest.deprecated", "_pytest.nodes", "_pytest.outcomes", "_pytest.main", "_pytest.terminal", "bdb", "os", "sys", "typing", "attr", "_pytest", "typing_extensions", "builtins", "html", "copy", "types", "traceback", "collections", "pprint", "warnings", "string", "itertools", "re", "_collections_abc", "_pytest._code", "_pytest._io", "_pytest._io.terminalwriter", "_pytest.config", "_pytest.hookspec", "_pytest.mark", "_typeshed", "abc", "argparse", "array", "attr.setters", "ctypes", "mmap", "time", "torch.ao.nn.quantized.dynamic", "torch.nn", "numpy", "torch.nn.intrinsic.quantized", "torch.ao.nn.quantized", "torch.distributed", "torch.ao.nn", "torch.nn.intrinsic", "torch.nn.intrinsic.qat", "multiprocessing.reduction", "torch.ao.nn.quantized.reference", "torch.nn.intrinsic.quantized.dynamic", "torch.ao.nn.qat.dynamic", "torch", "torch.ao.nn.qat", "torch.nn.functional"], "hash": "3ed1486e1bf1abecc3557497aad6062c2dabe2be6810b8a88d7e2475b98832f4", "id": "_pytest.runner", "ignore_all": true, "interface_hash": "a24175de07e77ab30c86aeb838f0572c801b2d0c4b021eaf70b946b512bbff22", "mtime": 1677478400, "options": {"allow_redefinition": false, "allow_untyped_globals": false, "always_false": [], "always_true": [], "bazel": false, "check_untyped_defs": false, "disable_bytearray_promotion": false, "disable_error_code": [], "disable_memoryview_promotion": false, "disabled_error_codes": [], "disallow_any_decorated": false, "disallow_any_explicit": false, "disallow_any_expr": false, "disallow_any_generics": false, "disallow_any_unimported": false, "disallow_incomplete_defs": false, "disallow_subclassing_any": false, "disallow_untyped_calls": false, "disallow_untyped_decorators": false, "disallow_untyped_defs": false, "enable_error_code": [], "enabled_error_codes": [], "follow_imports": "normal", "follow_imports_for_stubs": false, "ignore_errors": false, "ignore_missing_imports": false, "implicit_optional": false, "implicit_reexport": true, "local_partial_types": false, "mypyc": false, "platform": "linux", "plugins": [], "strict_concatenate": false, "strict_equality": false, "strict_optional": true, "warn_no_return": true, "warn_return_any": false, "warn_unreachable": false, "warn_unused_ignores": false}, "path": "/home/adi/.pyenv/versions/3.7.16/lib/python3.7/site-packages/_pytest/runner.py", "plugin_data": null, "size": 18058, "suppressed": [], "version_id": "1.0.1"}